{
    "WidgetStatusPanelWidget": {
        "id": "WidgetStatusPanelWidget",
        "file": "widgets/WidgetStatusPanelWidget.php",
        "roles": [],
        "missingRoles": true,
        "unguarded": true,
        "debugOnly": true,
        "unused": true,
        "previewGuarded": true
    },
    "artist_spotlight": {
        "id": "artist_spotlight",
        "file": "assets/js/widgets/ArtistSpotlightWidget.jsx",
        "roles": [
            "artist"
        ],
        "missingRoles": false,
        "unguarded": true,
        "debugOnly": false,
        "unused": false,
        "previewGuarded": true
    },
    "inbox_preview": {
        "id": "inbox_preview",
        "file": "assets/js/widgets/ArtistInboxPreviewWidget.jsx",
        "roles": [
            "artist"
        ],
        "missingRoles": false,
        "unguarded": true,
        "debugOnly": false,
        "unused": false,
        "previewGuarded": true
    },
    "revenue_summary": {
        "id": "revenue_summary",
        "file": "assets/js/widgets/ArtistRevenueSummaryWidget.jsx",
        "roles": [
            "artist"
        ],
        "missingRoles": false,
        "unguarded": true,
        "debugOnly": false,
        "unused": false,
        "previewGuarded": true
    },
    "artist_inbox_preview": {
        "id": "artist_inbox_preview",
        "file": "assets/js/widgets/ArtistInboxPreviewWidget.jsx",
        "roles": [
            "member"
        ],
        "missingRoles": false,
        "unguarded": true,
        "debugOnly": false,
        "unused": false,
        "previewGuarded": true
    },
    "event_chat": {
        "id": "event_chat",
        "file": "assets/js/widgets/EventChatWidget.jsx",
        "roles": [
            "member"
        ],
        "missingRoles": false,
        "unguarded": true,
        "debugOnly": false,
        "unused": false,
        "previewGuarded": true
    },
    "my_favorites": {
        "id": "my_favorites",
        "file": "assets/js/widgets/MyFavoritesWidget.jsx",
        "roles": [
            "member"
        ],
        "missingRoles": false,
        "unguarded": true,
        "debugOnly": false,
        "unused": false,
        "previewGuarded": true
    },
    "nearby_events_map": {
        "id": "nearby_events_map",
        "file": "assets/js/widgets/NearbyEventsMapWidget.jsx",
        "roles": [
            "member"
        ],
        "missingRoles": false,
        "unguarded": false,
        "debugOnly": false,
        "unused": false,
        "previewGuarded": true
    },
    "news_feed": {
        "id": "news_feed",
        "file": "widgets/ArtPulseNewsFeedWidget.php",
        "roles": [
            "member"
        ],
        "missingRoles": false,
        "unguarded": true,
        "debugOnly": false,
        "unused": false,
        "previewGuarded": true
    },
    "qa_checklist": {
        "id": "qa_checklist",
        "file": "widgets/QAChecklistWidget.php",
        "roles": [
            "member"
        ],
        "missingRoles": false,
        "unguarded": true,
        "debugOnly": false,
        "unused": false,
        "previewGuarded": true
    },
    "rsvp_button": {
        "id": "rsvp_button",
        "file": "assets/js/widgets/RSVPButton.jsx",
        "roles": [
            "member"
        ],
        "missingRoles": false,
        "unguarded": true,
        "debugOnly": false,
        "unused": false,
        "previewGuarded": true
    },
    "share_this_event": {
        "id": "share_this_event",
        "file": "assets/js/widgets/ShareThisEventWidget.jsx",
        "roles": [
            "member"
        ],
        "missingRoles": false,
        "unguarded": true,
        "debugOnly": false,
        "unused": false,
        "previewGuarded": true
    },
    "audience_crm": {
        "id": "audience_crm",
        "file": "assets/js/widgets/AudienceCRMWidget.jsx",
        "roles": [
            "organization"
        ],
        "missingRoles": false,
        "unguarded": true,
        "debugOnly": false,
        "unused": false,
        "previewGuarded": true
    },
    "branding_settings_panel": {
        "id": "branding_settings_panel",
        "file": "assets/js/widgets/OrgBrandingSettingsPanel.jsx",
        "roles": [
            "organization"
        ],
        "missingRoles": false,
        "unguarded": true,
        "debugOnly": false,
        "unused": false,
        "previewGuarded": true
    },
    "donor_activity": {
        "id": "donor_activity",
        "file": "widgets/DonorActivityWidget.php",
        "roles": [
            "organization"
        ],
        "missingRoles": false,
        "unguarded": true,
        "debugOnly": false,
        "unused": false,
        "previewGuarded": true
    },
    "embed_tool": {
        "id": "embed_tool",
        "file": "assets/js/widgets/EmbedToolWidget.jsx",
        "roles": [
            "organization"
        ],
        "missingRoles": false,
        "unguarded": true,
        "debugOnly": false,
        "unused": false,
        "previewGuarded": true
    },
    "org_widget_sharing": {
        "id": "org_widget_sharing",
        "file": "widgets/OrgWidgetSharingPanel.php",
        "roles": [
            "organization"
        ],
        "missingRoles": false,
        "unguarded": true,
        "debugOnly": false,
        "unused": false,
        "previewGuarded": true
    },
    "sponsor_display": {
        "id": "sponsor_display",
        "file": "widgets/SponsorDisplayWidget.php",
        "roles": [
            "organization"
        ],
        "missingRoles": false,
        "unguarded": true,
        "debugOnly": false,
        "unused": false,
        "previewGuarded": true
    },
    "sponsored_event_config": {
        "id": "sponsored_event_config",
        "file": "assets/js/widgets/SponsoredEventConfigWidget.jsx",
        "roles": [
            "organization"
        ],
        "missingRoles": false,
        "unguarded": true,
        "debugOnly": false,
        "unused": false,
        "previewGuarded": true
    }
}
